dict_utils/__init__.py
dict_utils/core.py
dictory-0.1.2.dist-info/licenses/LICENSE
dictory-0.1.2.dist-info/METADATA
dictory-0.1.2.dist-info/WHEEL
dictory-0.1.2.dist-info/top_level.txt
dictory-0.1.2.dist-info/RECORD
