Metadata-Version: 2.4
Name: dictory
Version: 0.1.2
Summary: A playful blend of dict and utility/library.
Requires-Python: >=3.13.3
License-File: LICENSE
Requires-Dist: mypy>=1.16.0
Requires-Dist: pre-commit>=4.2.0
Requires-Dist: pytest>=8.4.0
Provides-Extra: dev
Requires-Dist: pytest; extra == "dev"
Requires-Dist: pytest-cov; extra == "dev"
Requires-Dist: black; extra == "dev"
Requires-Dist: ruff; extra == "dev"
Requires-Dist: mypy; extra == "dev"
Requires-Dist: pre-commit>=4.2.0; extra == "dev"
Dynamic: license-file
